pyboltwood/__init__.py
pyboltwood/cloudsensor.py
pyboltwood-0.1.11.dist-info/LICENSE
pyboltwood-0.1.11.dist-info/METADATA
pyboltwood-0.1.11.dist-info/WHEEL
pyboltwood-0.1.11.dist-info/top_level.txt
pyboltwood-0.1.11.dist-info/RECORD
