Metadata-Version: 2.1
Name: pyboltwood
Version: 0.1.11
Summary: Official Boltwood Cloud Sensor III Serial API Python wrapper
Author-email: Adam Robichaud <arobichaud@diffractionlimited.com>
Project-URL: Homepage, https://github.com/diffraction-limited/pyboltwood
Project-URL: Issues, https://github.com/diffraction-limited/pyboltwood/issues
Project-URL: Documentation, https://diffraction-limited.github.io/pyboltwood
Classifier: Programming Language :: Python :: 3
Classifier: License :: OSI Approved :: MIT License
Classifier: Operating System :: OS Independent
Requires-Python: >=3.10
License-File: LICENSE
Requires-Dist: pyserial ~=3.5
